[{"brand":"Motorola","price":25000.0,"color":"Green","storage":128,"description":"Motorola Edge 40 is a flagship killer phone with 8GB RAM and 128GB storage in just INR 25000.","model":"Edge 40"},{"brand":"Realme","price":15000.0,"color":"Black","storage":64,"description":"Realme 11 is a flagship killer phone with 4GB RAM and 64GB storage in just INR 15000.","model":"11"},{"brand":"iPhone","price":175000.0,"color":"Silver","storage":1024,"description":"iPhone 14 Pro Max is a flagship killer phone with 12GB RAM and 1TB storage in just INR 175000.","model":"14 Pro Max"},{"brand":"samsung","price":25000.0,"color":"Black","storage":128,"description":"samsung 40 is a flagship killer phone with 8GB RAM and 128GB storage in just INR 25000.","model":"Edge s24"},{"brand":"Samsung","price":20000.0,"color":"Red","storage":134,"description":"Smasung S24","model":"s24"},{"brand":"Samsung","price":20000.0,"color":"Red","storage":134,"description":"Smasung S24","model":"s24"},{"brand":"Samsung","price":2000.0,"color":"Black","storage":186,"description":"sxbdgnvfzszsbf","model":"s25"},{"brand":"Poco","price":15000.0,"color":"Green","storage":567,"description":"Poco A34 with 567 storage and with a Green color","model":"A34"},{"brand":"Vivo","price":24000.0,"color":"Blue","storage":128,"description":"Vivo! QOO23 24000 128","model":"!QOO23"},{"brand":"Orange","price":1000000.0,"color":"VIBGYOR","storage":1024,"description":"BESTERS ZPHZONE","model":"sx69"},{"brand":"Orange","price":1000000.0,"color":"VIBGYOR","storage":1024,"description":"BESTERS ZPHZONE","model":"sx69"},{"brand":"Orange","price":1000000.0,"color":"VIBGYOR","storage":1024,"description":"BESTERS ZPHZONE","model":"sx69"},{"brand":"Orange","price":1000000.0,"color":"VIBGYOR","storage":1024,"description":"BESTERS ZPHZONE","model":"sx69"}]